cloudx_caas_api/__init__.py
cloudx_caas_api/app_management.py
cloudx_caas_api/cluster_management.py
cloudx_caas_api/package_management.py
cloudx_caas_api/repository_management.py
cloudx_iaas_api/__init__.py
cloudx_iaas_api/compute_management.py
cloudx_iaas_api/load_balancer_management.py
cloudx_iaas_api/network_management.py
cloudx_iaas_api/network_vpn_management.py
cloudx_iaas_api/storage_management.py
cloudx_nac_api-1.3.7.data/scripts/cloudx
cloudx_paas_api/__init__.py
cloudx_paas_api/api_gw_management.py
cloudx_paas_api/backup_restore_management.py
cloudx_paas_api/database_management.py
cloudx_paas_api/iam_management.py
cloudx_paas_api/logging_management.py
cloudx_paas_api/monitoring_management.py
cloudx_paas_api/service_mesh_management.py
cloudx_paas_api/smart_dns_management.py
cloudx_nac_api-1.3.7.dist-info/LICENSE
cloudx_nac_api-1.3.7.dist-info/METADATA
cloudx_nac_api-1.3.7.dist-info/WHEEL
cloudx_nac_api-1.3.7.dist-info/top_level.txt
cloudx_nac_api-1.3.7.dist-info/RECORD
