Metadata-Version: 2.1
Name: cloudx-nac-api
Version: 1.3.7
Summary: CloudX Digital Edge IaaS API package
Home-page: https://github.com/cloudx/iaas-api
Author: Umut Karabudak
Author-email: umut.karabudak@cloudx.com
License: UNKNOWN
Platform: UNKNOWN
Classifier: Programming Language :: Python :: 3
Classifier: License :: OSI Approved :: MIT License
Classifier: Operating System :: OS Independent
